drb/topics/sentinel1/__init__.py
drb/topics/sentinel1/_version.py
drb/topics/sentinel1/cortex.yml
drb/topics/sentinel1/auxiliary/__init__.py
drb/topics/sentinel1/auxiliary/cortex.yml
drb/topics/sentinel1/eof/__init__.py
drb/topics/sentinel1/eof/cortex.yml
drb/topics/sentinel1/level0/__init__.py
drb/topics/sentinel1/level0/cortex.yml
drb/topics/sentinel1/level1/__init__.py
drb/topics/sentinel1/level1/cortex.yml
drb/topics/sentinel1/level2/__init__.py
drb/topics/sentinel1/level2/cortex.yml
drb_topic_sentinel1-1.3.0.dist-info/LICENCE.txt
drb_topic_sentinel1-1.3.0.dist-info/METADATA
drb_topic_sentinel1-1.3.0.dist-info/WHEEL
drb_topic_sentinel1-1.3.0.dist-info/entry_points.txt
drb_topic_sentinel1-1.3.0.dist-info/top_level.txt
drb_topic_sentinel1-1.3.0.dist-info/RECORD
